README.md
setup.py
fasttextannotator/__init__.py
fasttextannotator.egg-info/PKG-INFO
fasttextannotator.egg-info/SOURCES.txt
fasttextannotator.egg-info/dependency_links.txt
fasttextannotator.egg-info/entry_points.txt
fasttextannotator.egg-info/not-zip-safe
fasttextannotator.egg-info/requires.txt
fasttextannotator.egg-info/top_level.txt