Metadata-Version: 2.1
Name: fasttextannotator
Version: 1.0.0
Summary: A python package that allows the user to annotate corpuses for FastText
Home-page: https://github.com/dust10141/fasttext-annotator
Author: Will Sackfield
Author-email: will.sackfield@gmail.com
License: MIT
Platform: UNKNOWN
